odoo/addons/ssi_accountant_general_audit_ws_ra140/README.rst
odoo/addons/ssi_accountant_general_audit_ws_ra140/__init__.py
odoo/addons/ssi_accountant_general_audit_ws_ra140/__manifest__.py
odoo/addons/ssi_accountant_general_audit_ws_ra140/data/accountant_financial_ratio_data.xml
odoo/addons/ssi_accountant_general_audit_ws_ra140/data/accountant_general_audit_worksheet_type_data.xml
odoo/addons/ssi_accountant_general_audit_ws_ra140/data/approval_template_data.xml
odoo/addons/ssi_accountant_general_audit_ws_ra140/data/ir_sequence_data.xml
odoo/addons/ssi_accountant_general_audit_ws_ra140/data/policy_template_data.xml
odoo/addons/ssi_accountant_general_audit_ws_ra140/data/sequence_template_data.xml
odoo/addons/ssi_accountant_general_audit_ws_ra140/models/__init__.py
odoo/addons/ssi_accountant_general_audit_ws_ra140/models/accountant_analytic_procedure_conclusion_category.py
odoo/addons/ssi_accountant_general_audit_ws_ra140/models/accountant_client_account_type.py
odoo/addons/ssi_accountant_general_audit_ws_ra140/models/accountant_financial_ratio.py
odoo/addons/ssi_accountant_general_audit_ws_ra140/models/ws_ra140.py
odoo/addons/ssi_accountant_general_audit_ws_ra140/models/ws_ra1401.py
odoo/addons/ssi_accountant_general_audit_ws_ra140/models/ws_ra1401_vertical_horizontal_analysis.py
odoo/addons/ssi_accountant_general_audit_ws_ra140/models/ws_ra1402.py
odoo/addons/ssi_accountant_general_audit_ws_ra140/models/ws_ra1402_ratio.py
odoo/addons/ssi_accountant_general_audit_ws_ra140/models/ws_ra140_analytic_procedure_conclusion.py
odoo/addons/ssi_accountant_general_audit_ws_ra140/security/ir.model.access.csv
odoo/addons/ssi_accountant_general_audit_ws_ra140/security/ir_module_category_data.xml
odoo/addons/ssi_accountant_general_audit_ws_ra140/security/ir_rule_data.xml
odoo/addons/ssi_accountant_general_audit_ws_ra140/security/res_group_data.xml
odoo/addons/ssi_accountant_general_audit_ws_ra140/static/description/icon.png
odoo14_addon_ssi_accountant_general_audit_ws_ra140-14.0.1.6.2.dev1.dist-info/METADATA
odoo14_addon_ssi_accountant_general_audit_ws_ra140-14.0.1.6.2.dev1.dist-info/WHEEL
odoo14_addon_ssi_accountant_general_audit_ws_ra140-14.0.1.6.2.dev1.dist-info/top_level.txt
odoo14_addon_ssi_accountant_general_audit_ws_ra140-14.0.1.6.2.dev1.dist-info/RECORD
